DemoPkgFrCrunch/CurrentMonth.py
DemoPkgFrCrunch/__init__.py
DemoPkgFrCrunch-0.0.1.dist-info/METADATA
DemoPkgFrCrunch-0.0.1.dist-info/WHEEL
DemoPkgFrCrunch-0.0.1.dist-info/top_level.txt
DemoPkgFrCrunch-0.0.1.dist-info/RECORD
