Metadata-Version: 2.1
Name: DemoPkgFrCrunch
Version: 0.0.1
Summary: Calculate current Month
Author: Ratnakar Kumbhar
Author-email: ratnakar.kumbhar@crunchyroll.com
Classifier: Programming Language :: Python :: 3
Classifier: License :: OSI Approved :: MIT License
Classifier: Operating System :: OS Independent
Requires-Python: >=3.7
